fast_gaussian_initialization-0.0.2.dist-info/licenses/LICENSE
fastgi/__init__.py
fastgi/config.py
fastgi/core.py
fastgi/io.py
fastgi/render.py
fastgi/viz.py
fast_gaussian_initialization-0.0.2.dist-info/METADATA
fast_gaussian_initialization-0.0.2.dist-info/WHEEL
fast_gaussian_initialization-0.0.2.dist-info/top_level.txt
fast_gaussian_initialization-0.0.2.dist-info/RECORD
