Metadata-Version: 2.4
Name: fast-gaussian-initialization
Version: 0.0.2
Summary: A library for fast CPU-based initialization of 3D Gaussian Splatting models from point clouds.
Author-email: rakaplay <161695371+rakaplay@users.noreply.github.com>
License-Expression: MIT
Classifier: Programming Language :: Python :: 3
Classifier: Operating System :: OS Independent
Classifier: Topic :: Scientific/Engineering :: Visualization
Requires-Python: >=3.9
License-File: LICENSE
Requires-Dist: numpy
Requires-Dist: scipy
Requires-Dist: scikit-learn
Requires-Dist: plyfile
Requires-Dist: matplotlib
Requires-Dist: tqdm
Requires-Dist: open3d
Dynamic: license-file
